airflow_provider_alembic/__init__.py
airflow_provider_alembic/hooks/__init__.py
airflow_provider_alembic/hooks/alembic.py
airflow_provider_alembic/operators/__init__.py
airflow_provider_alembic/operators/alembic.py
airflow_provider_alembic-1.0.0.dist-info/METADATA
airflow_provider_alembic-1.0.0.dist-info/WHEEL
airflow_provider_alembic-1.0.0.dist-info/entry_points.txt
airflow_provider_alembic-1.0.0.dist-info/top_level.txt
airflow_provider_alembic-1.0.0.dist-info/RECORD
