Metadata-Version: 2.1
Name: airflow-provider-alembic
Version: 1.0.0
Summary: Apache Airflow Alembic provider containing Operators & Hooks.
Home-page: https://github.com/astronomer/airflow-provider-alembic
Author: Fritz Davenport
Author-email: cse@astronomer.io
License: Apache License 2.0
Project-URL: Source Code, https://github.com/astronomer/airflow-provider-alembic
Project-URL: Homepage, https://github.com/astronomer/airflow-provider-alembic
Project-URL: Changelog, https://github.com/astronomer/airflow-provider-alembic/blob/main/CHANGELOG.md
Classifier: Environment :: Web Environment
Classifier: Intended Audience :: Developers
Classifier: License :: OSI Approved :: Apache Software License
Classifier: Operating System :: OS Independent
Classifier: Programming Language :: Python
Classifier: Programming Language :: Python :: 3
Classifier: Programming Language :: Python :: 3.7
Classifier: Programming Language :: Python :: 3.8
Classifier: Programming Language :: Python :: 3.9
Requires-Python: >=3.7
Requires-Dist: apache-airflow (>=2.2.0)
Requires-Dist: alembic
Provides-Extra: dev
Requires-Dist: mypy (>=0.800) ; extra == 'dev'
Requires-Dist: pytest ; extra == 'dev'
Requires-Dist: pre-commit ; extra == 'dev'
